ab_client/auth_client/__init__.py
ab_client/auth_client/clients/__init__.py
ab_client/auth_client/clients/async_client.py
ab_client/auth_client/clients/sync_client.py
ab_client/auth_client/exceptions/__init__.py
ab_client/auth_client/exceptions/http_exception.py
ab_client/auth_client/models/HTTPValidationError.py
ab_client/auth_client/models/OAuth2AuthorizeResponse.py
ab_client/auth_client/models/OAuth2TokenExposed.py
ab_client/auth_client/models/PKCEAuthorizeResponse.py
ab_client/auth_client/models/ValidationError.py
ab_client/auth_client/models/__init__.py
ab_client_auth_client-1.1.1.dist-info/METADATA
ab_client_auth_client-1.1.1.dist-info/WHEEL
ab_client_auth_client-1.1.1.dist-info/licenses/LICENSE
ab_client_auth_client-1.1.1.dist-info/RECORD
